ddnnife-0.10.0.dist-info/METADATA
ddnnife-0.10.0.dist-info/WHEEL
ddnnife/__init__.py
ddnnife/ddnnife.dll
ddnnife/ddnnife.py
ddnnife-0.10.0.dist-info/RECORD
