Metadata-Version: 2.4
Name: ddnnife
Version: 0.10.0
Summary: d-DNNF toolkit
License: LGPL-3.0-or-later
Project-URL: source, https://github.com/SoftVarE-Group/d-dnnf-reasoner
